byted_overpass_toutiao_novelsale_user_info/__init__.py
byted_overpass_toutiao_novelsale_user_info-0.0.1.dist-info/METADATA
byted_overpass_toutiao_novelsale_user_info-0.0.1.dist-info/WHEEL
byted_overpass_toutiao_novelsale_user_info-0.0.1.dist-info/top_level.txt
byted_overpass_toutiao_novelsale_user_info-0.0.1.dist-info/RECORD
